operation/__init__.py
operation/operation.py
tests/__init__.py
tests/test_operation.py
operation-0.0.4.dist-info/LICENSE
operation-0.0.4.dist-info/METADATA
operation-0.0.4.dist-info/WHEEL
operation-0.0.4.dist-info/top_level.txt
operation-0.0.4.dist-info/RECORD
