Metadata-Version: 2.1
Name: operation
Version: 0.0.4
Summary: A Railway pattern based operation package
Home-page: https://github.com/yoavabadi/operation
Author: Yoav Abadi
Author-email: yoavabadi@gmail.com
License: UNKNOWN
Platform: UNKNOWN
Classifier: Programming Language :: Python :: 3
Classifier: License :: OSI Approved :: MIT License
Classifier: Operating System :: OS Independent
Requires: schema
Requires-Python: >=3.6
